<?xml version="1.0" encoding="UTF-8"?>
<objects serializationModel="Studio.02.02.00">
	<object class="AudioFile" id="{a4b86b3e-a0c7-4950-910a-234b3ca0deec}">
		<property name="assetPath">
			<value>SFX_nursebot_dialogue-003.ogg</value>
		</property>
		<property name="frequencyInKHz">
			<value>96</value>
		</property>
		<property name="channelCount">
			<value>2</value>
		</property>
		<property name="length">
			<value>1.94996875</value>
		</property>
		<relationship name="masterAssetFolder">
			<destination>{93e57aa7-3ab8-4787-b546-95b25ce1b1e9}</destination>
		</relationship>
	</object>
</objects>
